odoo/addons/purchase_order_purchase_manager/README.rst
odoo/addons/purchase_order_purchase_manager/__init__.py
odoo/addons/purchase_order_purchase_manager/__manifest__.py
odoo/addons/purchase_order_purchase_manager/i18n/es.po
odoo/addons/purchase_order_purchase_manager/i18n/it.po
odoo/addons/purchase_order_purchase_manager/i18n/purchase_order_purchase_manager.pot
odoo/addons/purchase_order_purchase_manager/models/__init__.py
odoo/addons/purchase_order_purchase_manager/models/purchase_order.py
odoo/addons/purchase_order_purchase_manager/readme/CONTRIBUTORS.rst
odoo/addons/purchase_order_purchase_manager/readme/DESCRIPTION.rst
odoo/addons/purchase_order_purchase_manager/readme/USAGE.rst
odoo/addons/purchase_order_purchase_manager/static/description/icon.png
odoo/addons/purchase_order_purchase_manager/static/description/index.html
odoo/addons/purchase_order_purchase_manager/tests/__init__.py
odoo/addons/purchase_order_purchase_manager/tests/test_purchase_manager.py
odoo_addon_purchase_order_purchase_manager-16.0.1.0.1.2.dist-info/METADATA
odoo_addon_purchase_order_purchase_manager-16.0.1.0.1.2.dist-info/WHEEL
odoo_addon_purchase_order_purchase_manager-16.0.1.0.1.2.dist-info/top_level.txt
odoo_addon_purchase_order_purchase_manager-16.0.1.0.1.2.dist-info/RECORD
