Metadata-Version: 2.1
Name: odoo-addon-purchase-order-purchase-manager
Version: 16.0.1.0.1.2
Summary: Purchase Manager from Supplier in Purchase Order
Home-page: https://github.com/OCA/purchase-workflow
Author: Moduon, Odoo Community Association (OCA)
Author-email: support@odoo-community.org
License: LGPL-3
Platform: UNKNOWN
Classifier: Programming Language :: Python
Classifier: Framework :: Odoo
Classifier: Framework :: Odoo :: 16.0
Classifier: License :: OSI Approved :: GNU Lesser General Public License v3 (LGPLv3)
Classifier: Development Status :: 3 - Alpha
Requires-Python: >=3.10
Requires-Dist: odoo-addon-partner-purchase-manager <16.1dev,>=16.0dev
Requires-Dist: odoo <16.1dev,>=16.0a
